{"i":{"9oe-hdrUb":{"id":"9oe-hdrUb","type":"slide","setup":{"transparentBg":{"selectedKey":false},"bord":{"size":0,"rad":0},"bg":{"selectedKey":"fill","fill":{"opac":1,"rgb":"var(--TC3)"},"img":{"filt":{"opac":70,"gray":0,"blur":0,"tint":{"rgb":"#000000","opac":0.8}},"pos":{"type":"crop","fit":{"bg":{"color":{"rgb":"#FFF","opac":100}},"vali":"center","hali":"center"},"crop":{"poi":{"x":552,"y":360}}},"measures":{"size":{"width":1080,"height":720}}}}}},"k7dTD0SFDN":{"id":"k7dTD0SFDN","type":"interactive","subtype":"interactiveRichText","setup":{"frmeTp":{"selectedKey":"leftLine"},"bg":{"fill":{"opac":0,"rgb":"var(--TC3)"},"selectedKey":"fill"},"rType":"richtext","hali":"","vali":"middle","txt":{"rType":"richtext","val":{"ops":[{"attributes":{"color":"#217671","bold":true},"insert":"Introducción"},{"attributes":{"size":"large"},"insert":"\n"},{"attributes":{"size":"normal","align":"justify"},"insert":"\n"},{"attributes":{"color":"#000000","lang":"ES-CO"},"insert":"La Internet facilita que los documentos (Web) se encuentran interconectados por enlaces de hipertextos que se encuentran disponibles en la red, cuya interconexión es un desarrollo de la tecnología digital. Los recursos como wiki, blogs, Facebook, Twitter, entre otros, hacen parte de internet, no de la Web."},{"attributes":{"size":"normal","align":"justify"},"insert":"\n\n"}]}},"paddV1":64,"frmeColo":{"color":{"opac":1,"rgb":"#217671"}}}},"zGyoZPcSB":{"id":"zGyoZPcSB","type":"interactive","subtype":"interactiveImage","setup":{"img":{"filt":{"opac":100,"gray":0,"blur":0,"tint":{"rgb":"#FFF","opac":0}},"pos":{"type":"crop","fit":{"bg":{"color":{"rgb":"#FFF","opac":100},"gradient":{"angle":0,"opac":0.5,"stops":[{"color":"#000000","pos":0},{"color":"#000000","pos":100}]}},"vali":"center","hali":"center"},"crop":{"bg":{"color":{"rgb":"#FFF","opac":0},"gradient":{"angle":0,"opac":0.5,"stops":[{"color":"#000000","pos":0},{"color":"#000000","pos":100}]}},"poi":{"x":635,"y":456}},"mask":{"shape":1,"bg":{"color":{"rgb":"#FFF","opac":0},"gradient":{"angle":0,"opac":0.5,"stops":[{"color":"#000000","pos":0},{"color":"#000000","pos":100}]}}},"zoom":0},"measures":{"size":{"width":1500,"height":844}},"orig":{"rType":"asset","rSubType":"image","fileName":"plataforma-cadena-bloques-cardano.jpg","fileSize":1055828,"val":"mc-b116a26013e5429234f6173b6b7ee2c9.jpg","aid":"1VAxRDBlj"}},"zoom":{"selectedKey":false}}}},"v":"1"}